{"pageProps":{"data":"<h5>标题</h5>\n<p>通过 &lt;h[\\m]&gt; … &lt;/h[\\m]&gt; 标签进行定义的，其中 n 的值是从 1 到 6 ，分别表示六级标题。</p>\n<h5>斜体 和 粗体</h5>\n<p>粗体（ boldface ）和斜体（ italic ）文本在所有纸面交流中都变成了社交礼节所要求的。</p>\n<p>给文本添加粗体和斜体格式化效果的老派方法——这里将简要讨论，因为如果你选择查看源代码，那么将不可避免地会在许多 Web 站点的源代码中看到它，包括 &lt;b&gt;&lt;/b&gt; 和\n    &lt;i&gt;&lt;/i&gt; 标签对。对于粗体文本，将用 &lt;b&gt; 和 &lt;/b&gt; 标签包围文本。类似地，要使任何文本以斜体显示，将在 &lt;i&gt; 和 &lt;/i&gt;\n    标签内封闭它。尽管这种方法在浏览器中仍然会工作得很好，但它不像用于文本格式化的 CSS 样式规则那样灵活或强大，应该\n    <mark>避免使用</mark>。\n</p>\n<p>&lt;strong&gt; 和 &lt;em&gt; 标签被认为是 &lt;b&gt; 和 &lt;i&gt; 之上的改进，因为它们只暗示文本应该接受特殊的强调。它们没有明确规定应该如何实现这种效果。换句话说，浏览器不必把\n    &lt;strong&gt; 解释为意指粗体或者把 &lt;em&gt; 解释为意指斜体。这使 &lt;strong&gt; 和 &lt;em&gt; 更适合于 HTML5\n    ，因为它们给文本添加了含义，并且会影响文本的显示方式。</p>\n<h5>段落</h5>\n<p>其中 p 是 Paragraph （段落）的缩写，使用 &lt;p&gt; ～ &lt;/p&gt; 可以用来包裹文章的段落的主体内容。</p>\n<table id=\"Aa\">\n    <tr>\n        <th>属性</th>\n        <th>作用</th>\n    </tr>\n</table>\n<h5>常见</h5>\n<ul id=\"Ba\">\n</ul>\n<h6>del ins</h6>\n<p>del 和 ins 有两个重要是的属性：cite 、 datetime。 cite 属性不同于 cite 元素，用于提供一个 URL ，指向说明编辑原因的页面。datetime\n    属性提供编辑的时间，浏览器不会显示，不过可以提供一些背景信息。</p>\n<h6>meter</h6>\n<p>很像 progress ，可以用 meter 表示分数值或已知范围的测量结果。属性如下：</p>\n<ul>\n    <li>value 值，唯一必须包含的属性</li>\n    <li>min 最小</li>\n    <li>max 最大</li>\n    <li>low 下限</li>\n    <li>high 上限</li>\n    <li>optimum 设置最佳值</li>\n    <li>form 所属表单</li>\n</ul>\n<h6>引用它处内容</h6>\n<p>&lt;blockquote&gt; 与 &lt;/blockquote&gt; 之间的所有文本都会从常规文本中分离出来，经常会在左、右两边进行缩进（增加外边距），而且有时会使用斜体。也就是说，块引用拥有它们自己的空间。\n</p>\n<h5>文字的滚动</h5>\n<p>使用 marquee 元素可以实现文字的滚动。</p>\n<code class=\"c\">\n    <span class=\"p\">&lt;marquee style=\"width:xx;height: xx;\" scrollamount=\"2\" direction=\"up\"\n        align=\"right\"&gt;</span>\n</code>\n<ul>\n    <li>bg color 属性设定活动字幕的背景颜色，背景颜色可用 RGB 、 16 进制值的格式或颜色名称来设定</li>\n    <li>width 用于设置滚动文本框的宽度，输入一个数值后从后面的单选框选择 in Pixels （按像素）或是 in Percent （按百分比）</li>\n    <li>height 用于设置滚动文本框的高度，输入一个数值后从后面的单选框选择 in Pixels （按像素）或是 in Percent （按百分比）</li>\n    <li>loop 属性设定滚动的次数，当 loop=-1 表示一直滚动下去，默认为 -1</li>\n    <li>hspace 、 vspace 设定活动字幕里所在的位置距离父容器垂直边框、竖屏的距离</li>\n</ul>\n<p>设定 &lt;marquee&gt; 标签内容的对齐方式可选参数如下。</p>\n<ul>\n    <li>absbottom ：绝对底部对齐（与 g 、 p 等字母的最下端对齐）</li>\n    <li>absmiddle ：绝对中央对齐</li>\n    <li>baseline ：底线对齐</li>\n    <li>bottom ：底部对齐（默认）</li>\n    <li>left ：左对齐</li>\n    <li>middle ：中间对齐</li>\n    <li>right ：右对齐</li>\n    <li>texttop ：顶线对齐</li>\n    <li>top ：顶部对齐</li>\n</ul>\n<marquee behavior=\"alternate\" direction=\"up\"\n    style=\"width: 12rem;background: chartreuse;height: 2rem;text-align: center;\" scrollamount=\"2\" align=\"center\">\n    <p>........ 。</p>\n    <p>....... 。</p>\n    <p>...... 。</p>\n    <p>..... 。</p>\n    <p>.... 。</p>\n    <p>... 。</p>\n    <p>.. 。</p>\n    <p>. 。</p>\n</marquee>\n<p>behavior 属性设置 marquee 的滚动的方式 </p>\n<ul>\n    <li>scroll ：循环滚动</li>\n    <li>slide ：单次滚动</li>\n    <li>alternate ：来回滚动</li>\n</ul>\n\n<script>\n    var Aa = [\n        ['class=class ', ' 设置类属性 ',],\n        ['id=id ', ' 设置 ID 属性 ',],\n        ['style=style ', ' 设置行内样式 ',],\n        ['title=title ', ' 设置标题 ',],\n        ['dir=dir ', ' 设置段落文字的显示方向 ',],\n        ['lang=lang ', ' 设置语言种类 ',],\n        ['accesskey=key ', ' 设置快捷键 ',],\n        ['tabindex=n ', ' 设置 Tab 键在控件中的移动顺序 ',],\n        ['contenteditable=bool ', ' 设置元素是否可编辑 ',],\n        ['contextmenu=id ', ' 指定 context menu ',],\n        ['draggable=bool ', ' 设置是否可拖拽 ',],\n        ['dropzone=value ', ' 设置是否可拖放 ',],\n        ['hidden ', ' 设置隐藏元素 ',],\n        ['spellcheck=bool ', ' 检查语法拼写 ',],\n        ['IE 扩展属性 ', ' 用于设定 IE 扩展属性 ',],\n    ];\n    _MiMethod.td('Aa', Aa);\n    var Ba = ['&lt;abbr>、&lt;/abbr>表示缩写 ', '&lt;address>地址 ', '&lt;bdi>文档方向 ( 不受父级影响 )', '&lt;br>换行 ', '&lt;bro>文档方向 包含 dir 属性，取值包括 ltr （由左向右）和 rtl （由右向左） ', '&lt;cite>引用其它作品标题 ', '&lt;code>、 &lt;var>、 &lt;samp>、 &lt;kbd>：表示输入和输出 ', '&lt;del>已删除的内容 ', '&lt;dfn>、&lt;/dfn>定义术语 ', '&lt;em>、&lt;/em>：强调的（斜体）文本。 ', '&lt;hr>主题分割线 ', '&lt;ins>已添加的内容 ', '&lt;mark>突出显示 ', '&lt;meter>代表投票结果。与 progress 类似，包含 value 、 min 、 max 、 low 、 high 、 optimum 、 form 属性 ', '&lt;pre>、&lt;/pre>：预先格式化的（通常是等宽的）文本，保留空格和换行符。 ', '&lt;progress>完成度，表水一个进度条，支持 max 、 value 、 form 属性 ', '&lt;q>、&lt;/q>定义短的引用 ', '&lt;ruby>、&lt;rt>、&lt;rp>、&lt;/rp>、&lt;rp >、&lt;/rp>、&lt;/rt>、&lt;/ruby>注释 ', '&lt;small>、&lt;/small>添加小号文本 ', '&lt;strong>、&lt;/strong>：醒目的（粗体）文本。 ', '&lt;sup>、&lt;/sup>：上标文本。 ', '&lt;sub>、&lt;/sub>：下标文本。 ', '&lt;span>段中元素 ', '&lt;time>表示时间和日期，可包含 datetime 属性，来告诉浏览器时间 ', '&lt;u>、&lt;/u>: 下划线 ', '&lt;wbr>智能换行 ',]\n    _MiMethod.li('Ba', Ba);\n</script>","pageTitle":"h-j-c ✈︎✈︎ html ✈︎✈︎ 基础","title":"文本"},"__N_SSG":true}